<?xml version="1.0" encoding="utf-8" ?>
<dwsync>
<file name="index.php" server="metimi.com/x-mad.com/" local="129628461869944626" remote="129628102200000000" Dst="-1" />
<file name="index.php" server="set2upg.com/public_html/" local="129742147237823530" remote="129750657600000000" Dst="-1" />
<file name="index.php" server="x-mad.com/public_html/" local="129904102320935234" remote="129903814200000000" Dst="2" />
<file name="xmadscript.js" server="x-mad.com/public_html/" local="129904054063391352" remote="129903766200000000" Dst="2" />
<file name="index.php" server="C:/xampp/htdocs/" local="129902107843382748" remote="129902107840000000" Dst="2" />
<file name="xmadscript.js" server="C:/xampp/htdocs/" local="129902112548511866" remote="129902112540000000" Dst="2" />
<file name="recent.txt" server="x-mad.com/public_html/" local="129902999670172323" remote="129903768000000000" Dst="2" />
<file name="getmoviecovers.php" server="x-mad.com/public_html/" local="129904000038301294" remote="129903712200000000" Dst="2" />
<file name="favicon.ico" server="x-mad.com/public_html/" local="129903702193646093" remote="129903415200000000" Dst="2" />
<file name="getmusiccovers.php" server="x-mad.com/public_html/" local="129904036208730124" remote="129903748200000000" Dst="2" />
<file name="searchstuff.php" server="x-mad.com/public_html/" local="129904103071608170" remote="129903814800000000" Dst="2" />
<file name="xmad.css" server="x-mad.com/public_html/" local="129904050112325364" remote="129903762600000000" Dst="2" />
<file name="functions.php" server="x-mad.com/public_html/" local="129904003538571498" remote="129903715800000000" Dst="2" />
<file name=".htaccess" server="x-mad.com/public_html/" local="129904445086730316" remote="129904156800000000" Dst="2" />
<file name="redirect.php" server="x-mad.com/public_html/" local="129904445019836490" remote="129904156800000000" Dst="2" />
</dwsync>